setup.py
wsgixhtml2html/__init__.py
wsgixhtml2html/xhtml.py
wsgixhtml2html.egg-info/PKG-INFO
wsgixhtml2html.egg-info/SOURCES.txt
wsgixhtml2html.egg-info/dependency_links.txt
wsgixhtml2html.egg-info/top_level.txt
