Metadata-Version: 1.0
Name: wsgixhtml2html
Version: 0.1-1
Summary: WSGI middleware to serve XHTML pages as HTML for old browsers
Home-page: UNKNOWN
Author: chrysn
Author-email: chrysn@fsfe.org
License: X11
Platform: UNKNOWN
